locate_pixelcolor_cpppragma/README.md
locate_pixelcolor_cpppragma/__init__.py
locate_pixelcolor_cpppragma/clooppra.dll
locate_pixelcolor_cpppragma/requirements.txt
locate_pixelcolor_cpppragma/thirdparty.json
locate_pixelcolor_cpppragma-0.12.dist-info/LICENSE.rst
locate_pixelcolor_cpppragma-0.12.dist-info/METADATA
locate_pixelcolor_cpppragma-0.12.dist-info/WHEEL
locate_pixelcolor_cpppragma-0.12.dist-info/top_level.txt
locate_pixelcolor_cpppragma-0.12.dist-info/RECORD
