Metadata-Version: 2.1
Name: locate-pixelcolor-cpppragma
Version: 0.12
Summary: Detect colors in images - 20 x faster than Numpy / 430 x faster than PIL
Home-page: https://github.com/hansalemaos/locate_pixelcolor_cpppragma
Author: Johannes Fischer
Author-email: aulasparticularesdealemaosp@gmail.com
License: MIT
Keywords: cpp,c++,image,search,parallel,rgb
Classifier: Development Status :: 4 - Beta
Classifier: Programming Language :: Python :: 3 :: Only
Classifier: Programming Language :: Python :: 3.10
Classifier: Topic :: Software Development :: Libraries :: Python Modules
Classifier: Topic :: Utilities
License-File: LICENSE.rst
Requires-Dist: numpy
